objectproxy/__init__.py
object_proxy-0.1a1.dist-info/LICENSE
object_proxy-0.1a1.dist-info/METADATA
object_proxy-0.1a1.dist-info/WHEEL
object_proxy-0.1a1.dist-info/top_level.txt
object_proxy-0.1a1.dist-info/zip-safe
object_proxy-0.1a1.dist-info/RECORD
