Metadata-Version: 2.1
Name: object-proxy
Version: 0.1a1
Summary: A minimalistic yet powerful object proxying utility
Home-page: https://github.com/aviksama/objectproxy
Author: Avik Samaddar
Author-email: eml2avik@gmail.com
License: UNKNOWN
Keywords: python objectproxy
Platform: UNKNOWN
Classifier: Programming Language :: Python
Classifier: Development Status :: 3 - Alpha
Classifier: Environment :: Console
Classifier: Intended Audience :: Developers
Classifier: License :: OSI Approved :: MIT License
Classifier: Programming Language :: Python :: 2.7
Classifier: Programming Language :: Python :: 3
Classifier: Programming Language :: Python :: 3.4
Classifier: Programming Language :: Python :: 3.5
Classifier: Programming Language :: Python :: 3.6
